suricata_check_design_principles/__init__.py
suricata_check_design_principles/_version.py
suricata_check_design_principles/checkers/__init__.py
suricata_check_design_principles/checkers/principle/__init__.py
suricata_check_design_principles/checkers/principle/_utils.py
suricata_check_design_principles/checkers/principle/ml.py
suricata_check_design_principles/checkers/principle/principle.py
suricata_check_design_principles/data/principle_ml_checker.pkl
suricata_check_design_principles-7.0.0b0.dist-info/licenses/LICENSE
suricata_check_design_principles-7.0.0b0.dist-info/licenses/NOTICE
suricata_check_design_principles-7.0.0b0.dist-info/METADATA
suricata_check_design_principles-7.0.0b0.dist-info/WHEEL
suricata_check_design_principles-7.0.0b0.dist-info/top_level.txt
suricata_check_design_principles-7.0.0b0.dist-info/RECORD
